{
  "aerotechdirect": {
    "count": 253.99998491512224,
    "samples": 692,
    "stock": 0.0,
    "streak": 0,
    "unmatched": 0.0,
    "updated_at": "2026-07-02T19:34:14+00:00"
  },
  "amw": {
    "count": 279.9999999999999,
    "samples": 562,
    "stock": 130.99999999999994,
    "streak": 0,
    "unmatched": 0.9999999999999998,
    "updated_at": "2026-07-02T19:34:14+00:00"
  },
  "balsa_machining": {
    "count": 204.0,
    "samples": 686,
    "stock": 55.000000000013536,
    "streak": 0,
    "unmatched": 0.0,
    "updated_at": "2026-07-02T19:34:14+00:00"
  },
  "buyrocketmotors": {
    "count": 280.9999999999999,
    "samples": 667,
    "stock": 109.0023784097547,
    "streak": 0,
    "unmatched": 0.0,
    "updated_at": "2026-07-02T19:34:14+00:00"
  },
  "csrocketry": {
    "count": 557.0000000566962,
    "samples": 672,
    "stock": 237.99999989920695,
    "streak": 0,
    "unmatched": 1.0,
    "updated_at": "2026-07-02T19:34:14+00:00"
  },
  "loki": {
    "count": 50.0,
    "samples": 699,
    "stock": 29.999999999999993,
    "streak": 0,
    "unmatched": 0.0,
    "updated_at": "2026-07-02T19:34:14+00:00"
  },
  "moto_joe": {
    "count": 527.9999999999998,
    "samples": 562,
    "stock": 4.000000000000002,
    "streak": 0,
    "unmatched": 1.0,
    "updated_at": "2026-07-02T19:34:14+00:00"
  },
  "newcenturyrocketry": {
    "count": 95.0,
    "samples": 342,
    "stock": 68.00000000000003,
    "streak": 0,
    "unmatched": 0.0,
    "updated_at": "2026-07-02T19:34:14+00:00"
  },
  "performancehobbies": {
    "count": 596.9999999999998,
    "samples": 699,
    "stock": 113.00000000000003,
    "streak": 0,
    "unmatched": 3.000000000000001,
    "updated_at": "2026-07-02T19:34:14+00:00"
  },
  "sirius": {
    "count": 308.0000000000001,
    "samples": 540,
    "stock": 162.1750999427345,
    "streak": 0,
    "unmatched": 1.0,
    "updated_at": "2026-07-02T19:34:14+00:00"
  },
  "wildman": {
    "count": 489.0000000000759,
    "samples": 652,
    "stock": 167.00000123626035,
    "streak": 0,
    "unmatched": 1.9999999999999996,
    "updated_at": "2026-07-02T19:34:14+00:00"
  }
}